{"cameraMode":{"drawMode":0,"name":"Shaded","section":"Shading Mode"},"sceneLighting":true,"audioPlay":false,"sceneViewState":{"m_AlwaysRefresh":false,"showFog":false,"showSkybox":true,"showFlares":true,"showImageEffects":true,"showParticleSystems":true,"showVisualEffectGraphs":true,"m_FxEnabled":true},"in2DMode":false,"pivot":{"x":-0.9521636962890625,"y":-33.727638244628909,"z":-194.7671661376953},"rotation":{"x":0.3734555244445801,"y":0.4743850529193878,"z":-0.2323213666677475,"w":0.7625736594200134},"size":252.78976440429688,"orthographic":false}